
{
    "resourceType": "Parameters",
    "id": "datos_niño_madre",
    "parameter": [
        {
            //Régimen de Afiliación --> RegAfiPer	
            "name": "RegAfiPer",
            "valueString": "...."
        },
        {
            //Aseguradora	 -->  AsegPer	
            "name": "AsegPer",
            "valueString": "...."
        }

       
    ]
}
	
	

--------------------------------------------------------------------------------

    Régimen de Afiliación 	RegAfiPer	
    Aseguradora	AsegPer	


    Autoriza llamadas telefónicas	AutLlaPer	
    Autoriza envío Email	AutEmaPer	


    Condición de la mujer	ConMujPer			
    Régimen de Afiliación Madre	RegAfiMad	
    Aseguradora Madre	AsegMad		
    Pertenencia étnica Madre	PerEtnMad

    Semanas de gestación	SemGesper
    Lugar de atención del parto	LugParPer
    ¿Otro Cuál? 	OtrLugPar		
        
	
	
	
	
	
	
	
